idaes_ui/__init__.py
idaes_ui/fv/README.md
idaes_ui/fv/__init__.py
idaes_ui/fv/conftest.py
idaes_ui/fv/diagnostic_example.py
idaes_ui/fv/errors.py
idaes_ui/fv/example.py
idaes_ui/fv/flowsheet.py
idaes_ui/fv/fsvis.py
idaes_ui/fv/model_server.py
idaes_ui/fv/persist.py
idaes_ui/fv/save_diagram_screenshot.py
idaes_ui/fv/icons/__init__.py
idaes_ui/fv/icons/icons.py
idaes_ui/fv/icons/positioning.py
idaes_ui/fv/mappings/mappings.json
idaes_ui/fv/models/__init__.py
idaes_ui/fv/models/base.py
idaes_ui/fv/models/cli.py
idaes_ui/fv/models/diag.py
idaes_ui/fv/models/diagnostics_toolbox_report.py
idaes_ui/fv/models/flowsheet.py
idaes_ui/fv/models/issues.py
idaes_ui/fv/models/settings.py
idaes_ui/fv/models/stats.py
idaes_ui/fv/models/tests/__init__.py
idaes_ui/fv/models/tests/test_base.py
idaes_ui/fv/models/tests/test_diag.py
idaes_ui/fv/models/tests/test_issues.py
idaes_ui/fv/models/tests/test_stats.py
idaes_ui/fv/static/idaes-logo.ico
idaes_ui/fv/static/index.html
idaes_ui/fv/static/assets/allPaths-01c9bf3a.js
idaes_ui/fv/static/assets/allPaths-0681ee5e.js
idaes_ui/fv/static/assets/allPaths-0bc9c7ab.js
idaes_ui/fv/static/assets/allPaths-1ec962a5.js
idaes_ui/fv/static/assets/allPaths-214b7e00.js
idaes_ui/fv/static/assets/allPaths-22e1146c.js
idaes_ui/fv/static/assets/allPaths-2c6dee0e.js
idaes_ui/fv/static/assets/allPaths-31cd9eea.js
idaes_ui/fv/static/assets/allPaths-43eadd12.js
idaes_ui/fv/static/assets/allPaths-49eb1853.js
idaes_ui/fv/static/assets/allPaths-4a93b574.js
idaes_ui/fv/static/assets/allPaths-54284cc9.js
idaes_ui/fv/static/assets/allPaths-55ece038.js
idaes_ui/fv/static/assets/allPaths-59afe831.js
idaes_ui/fv/static/assets/allPaths-63388724.js
idaes_ui/fv/static/assets/allPaths-6db4a51b.js
idaes_ui/fv/static/assets/allPaths-72f5bd5b.js
idaes_ui/fv/static/assets/allPaths-73e45bb5.js
idaes_ui/fv/static/assets/allPaths-74f74b36.js
idaes_ui/fv/static/assets/allPaths-755d17ce.js
idaes_ui/fv/static/assets/allPaths-7566af35.js
idaes_ui-0.25.10.dist-info/licenses/LICENSE.md
idaes_ui-0.25.10.dist-info/METADATA
idaes_ui-0.25.10.dist-info/WHEEL
idaes_ui-0.25.10.dist-info/top_level.txt
idaes_ui-0.25.10.dist-info/RECORD
