Metadata-Version: 2.4
Name: idaes-ui
Version: 0.25.10
Summary: IDAES UI
Author: The IDAES Project
License: BSD
Project-URL: github, https://github.com/idaes/idaes-ui
Project-URL: issues, https://github.com/idaes/idaes-ui/issues
Keywords: IDAES,energy systems,chemical engineering,process modeling
Classifier: Development Status :: 3 - Alpha
Classifier: Intended Audience :: End Users/Desktop
Classifier: Intended Audience :: Science/Research
Classifier: License :: OSI Approved :: BSD License
Classifier: Natural Language :: English
Classifier: Operating System :: MacOS
Classifier: Operating System :: Microsoft :: Windows
Classifier: Operating System :: Unix
Classifier: Programming Language :: Python
Classifier: Programming Language :: Python :: 3
Classifier: Programming Language :: Python :: 3.9
Classifier: Programming Language :: Python :: 3.10
Classifier: Programming Language :: Python :: 3.11
Classifier: Programming Language :: Python :: 3.12
Classifier: Programming Language :: Python :: 3.13
Classifier: Programming Language :: Python :: Implementation :: CPython
Classifier: Topic :: Scientific/Engineering :: Mathematics
Classifier: Topic :: Scientific/Engineering :: Chemistry
Classifier: Topic :: Software Development :: Libraries :: Python Modules
Requires-Python: >=3.9
License-File: LICENSE.md
Requires-Dist: setuptools
Requires-Dist: pydantic~=2.0
Requires-Dist: pint<0.25
Requires-Dist: nest_asyncio
Requires-Dist: IPython
Requires-Dist: playwright
Provides-Extra: testing
Requires-Dist: pytest; extra == "testing"
Requires-Dist: pytest-icdiff>=0.7; extra == "testing"
Requires-Dist: pytest-playwright==0.4.4; extra == "testing"
Requires-Dist: requests==2.31.0; extra == "testing"
Provides-Extra: pkg
Requires-Dist: build; extra == "pkg"
Requires-Dist: twine; extra == "pkg"
Dynamic: license-file
